uunonymous/__init__.py
uunonymous/dummy.py
uunonymous/uunonymous.py
UUnonymous-0.0.4.dist-info/METADATA
UUnonymous-0.0.4.dist-info/WHEEL
UUnonymous-0.0.4.dist-info/top_level.txt
UUnonymous-0.0.4.dist-info/RECORD
