Metadata-Version: 2.1
Name: UUnonymous
Version: 0.0.4
Summary: A tool to substitue patterns/names in a file tree
Home-page: https://github.com/UtrechtUniversity/uunonymous
Author: C.S. Kaandorp
Author-email: c.s.kaandorp@uu.nl
License: MIT
Platform: UNKNOWN
Requires-Python: >=3.6
